.gitignore
PyPI.md
README.md
gen_pyproject_toml.py
pyproject.toml
.github/workflows/update_dependencies.yaml
.github/workflows/weekly_release.yaml
src/jijzept_sdk/__init__.py
src/jijzept_sdk/__main__.py
src/jijzept_sdk/_version.py
src/jijzept_sdk.egg-info/PKG-INFO
src/jijzept_sdk.egg-info/SOURCES.txt
src/jijzept_sdk.egg-info/dependency_links.txt
src/jijzept_sdk.egg-info/entry_points.txt
src/jijzept_sdk.egg-info/requires.txt
src/jijzept_sdk.egg-info/top_level.txt