Metadata-Version: 2.4
Name: jijzept_sdk
Version: 2025.11.4
Summary: Free development kit provided by JijZept.
Author-email: "Jij Inc." <info@j-ij.com>
Classifier: Operating System :: POSIX :: Linux
Classifier: Programming Language :: Python :: 3 :: Only
Classifier: Programming Language :: Python :: 3.10
Classifier: Programming Language :: Python :: 3.11
Classifier: Programming Language :: Python :: 3.12
Requires-Python: <3.13,>=3.10
Requires-Dist: jijmodeling==1.14.0
Requires-Dist: ommx==2.0.11
Provides-Extra: all
Requires-Dist: ommx-fixstars-amplify-adapter==0.3.1; extra == "all"
Requires-Dist: ommx-da4-adapter==0.1.1; extra == "all"
Requires-Dist: ommx-dwave-adapter==0.1.1; extra == "all"
Requires-Dist: ommx-gurobipy-adapter==0.2.1; extra == "all"
Requires-Dist: ommx-highs-adapter==2.0.11; extra == "all"
Requires-Dist: ommx-python-mip-adapter==2.0.11; python_version < "3.12" and extra == "all"
Requires-Dist: ommx-openjij-adapter==2.0.11; extra == "all"
Requires-Dist: ommx-pyscipopt-adapter==2.0.11; extra == "all"
Requires-Dist: minto==1.4.1; extra == "all"
Requires-Dist: qamomile==0.8.0; extra == "all"
Requires-Dist: jupyterlab; extra == "all"
Provides-Extra: amplify
Requires-Dist: ommx-fixstars-amplify-adapter==0.3.1; extra == "amplify"
Provides-Extra: da4
Requires-Dist: ommx-da4-adapter==0.1.1; extra == "da4"
Provides-Extra: dwave
Requires-Dist: ommx-dwave-adapter==0.1.1; extra == "dwave"
Provides-Extra: gurobi
Requires-Dist: ommx-gurobipy-adapter==0.2.1; extra == "gurobi"
Provides-Extra: highs
Requires-Dist: ommx-highs-adapter==2.0.11; extra == "highs"
Provides-Extra: mip
Requires-Dist: ommx-python-mip-adapter==2.0.11; extra == "mip"
Provides-Extra: openjij
Requires-Dist: ommx-openjij-adapter==2.0.11; extra == "openjij"
Provides-Extra: scip
Requires-Dist: ommx-pyscipopt-adapter==2.0.11; extra == "scip"
Provides-Extra: minto
Requires-Dist: minto==1.4.1; extra == "minto"
Provides-Extra: qamomile
Requires-Dist: qamomile==0.8.0; extra == "qamomile"
Provides-Extra: lab
Requires-Dist: jupyterlab; extra == "lab"
